MANIFEST.in
README.rst
setup.py
pinax_theme_bootstrap/__init__.py
pinax_theme_bootstrap/conf.py
pinax_theme_bootstrap/context_processors.py
pinax_theme_bootstrap/models.py
pinax_theme_bootstrap.egg-info/PKG-INFO
pinax_theme_bootstrap.egg-info/SOURCES.txt
pinax_theme_bootstrap.egg-info/dependency_links.txt
pinax_theme_bootstrap.egg-info/not-zip-safe
pinax_theme_bootstrap.egg-info/requires.txt
pinax_theme_bootstrap.egg-info/top_level.txt
pinax_theme_bootstrap/locale/fr/LC_MESSAGES/django.mo
pinax_theme_bootstrap/locale/fr/LC_MESSAGES/django.po
pinax_theme_bootstrap/locale/ja/LC_MESSAGES/django.mo
pinax_theme_bootstrap/locale/ja/LC_MESSAGES/django.po
pinax_theme_bootstrap/locale/zh_CN/LC_MESSAGES/django.mo
pinax_theme_bootstrap/locale/zh_CN/LC_MESSAGES/django.po
pinax_theme_bootstrap/management/__init__.py
pinax_theme_bootstrap/management/commands/__init__.py
pinax_theme_bootstrap/management/commands/copy_from_theme.py
pinax_theme_bootstrap/static/pinax/css/theme.css
pinax_theme_bootstrap/static/pinax/js/theme.js
pinax_theme_bootstrap/templates/404.html
pinax_theme_bootstrap/templates/500.html
pinax_theme_bootstrap/templates/_account_bar.html
pinax_theme_bootstrap/templates/_messages.html
pinax_theme_bootstrap/templates/site_base.html
pinax_theme_bootstrap/templates/account/_login_sidebar.html
pinax_theme_bootstrap/templates/account/_signup_sidebar.html
pinax_theme_bootstrap/templates/account/base.html
pinax_theme_bootstrap/templates/account/delete.html
pinax_theme_bootstrap/templates/account/email_confirm.html
pinax_theme_bootstrap/templates/account/email_confirmation_sent.html
pinax_theme_bootstrap/templates/account/email_confirmed.html
pinax_theme_bootstrap/templates/account/login.html
pinax_theme_bootstrap/templates/account/logout.html
pinax_theme_bootstrap/templates/account/password_change.html
pinax_theme_bootstrap/templates/account/password_reset.html
pinax_theme_bootstrap/templates/account/password_reset_sent.html
pinax_theme_bootstrap/templates/account/password_reset_token.html
pinax_theme_bootstrap/templates/account/password_reset_token_fail.html
pinax_theme_bootstrap/templates/account/settings.html
pinax_theme_bootstrap/templates/account/signup.html
pinax_theme_bootstrap/templates/account/signup_closed.html
