Metadata-Version: 1.1
Name: pinax-theme-bootstrap
Version: 7.10.0
Summary: a theme for Pinax based on Bootstrap
Home-page: http://github.com/pinax/pinax-theme-bootstrap
Author: Pinax Team
Author-email: developers@pinaxproject.com
License: MIT
Platform: UNKNOWN
Classifier: Development Status :: 5 - Production/Stable
Classifier: Environment :: Web Environment
Classifier: Intended Audience :: Developers
Classifier: License :: OSI Approved :: MIT License
Classifier: Operating System :: OS Independent
Classifier: Programming Language :: Python
Classifier: Framework :: Django
